<annotation>
	<folder>WH_data</folder>
	<filename>08433.JPEG</filename>
	<source>
		<database>WH Data</database>
		<annotation>WH</annotation>
		<image>flickr</image>
		<flickrid>NULL</flickrid>
	</source>
	<owner>
		<flickrid>NULL</flickrid>
		<name>WH</name>
	</owner>
	<size>
		<width>817</width>
		<height>577</height>
		<depth>3</depth>
	</size>
		<segmented>0</segmented>
	<object>
		<name>n</name>
		<pose>Unspecified</pose>
		<truncated>1</truncated>
		<difficult>0</difficult>
		<bndbox>
			<xmin>346</xmin>
			<ymin>226</ymin>
			<xmax>395</xmax>
			<ymax>259</ymax>
		</bndbox>
	</object>
	<object>
		<name>n</name>
		<pose>Unspecified</pose>
		<truncated>1</truncated>
		<difficult>0</difficult>
		<bndbox>
			<xmin>408</xmin>
			<ymin>143</ymin>
			<xmax>449</xmax>
			<ymax>177</ymax>
		</bndbox>
	</object>
	<object>
		<name>n</name>
		<pose>Unspecified</pose>
		<truncated>1</truncated>
		<difficult>0</difficult>
		<bndbox>
			<xmin>571</xmin>
			<ymin>105</ymin>
			<xmax>650</xmax>
			<ymax>151</ymax>
		</bndbox>
	</object>
	<object>
		<name>n</name>
		<pose>Unspecified</pose>
		<truncated>1</truncated>
		<difficult>0</difficult>
		<bndbox>
			<xmin>717</xmin>
			<ymin>177</ymin>
			<xmax>772</xmax>
			<ymax>204</ymax>
		</bndbox>
	</object>
</annotation>