<annotation>
	<folder>WH_data</folder>
	<filename>10769.JPEG</filename>
	<source>
		<database>WH Data</database>
		<annotation>WH</annotation>
		<image>flickr</image>
		<flickrid>NULL</flickrid>
	</source>
	<owner>
		<flickrid>NULL</flickrid>
		<name>WH</name>
	</owner>
	<size>
		<width>820</width>
		<height>581</height>
		<depth>3</depth>
	</size>
		<segmented>0</segmented>
	<object>
		<name>n</name>
		<pose>Unspecified</pose>
		<truncated>1</truncated>
		<difficult>0</difficult>
		<bndbox>
			<xmin>576</xmin>
			<ymin>136</ymin>
			<xmax>633</xmax>
			<ymax>164</ymax>
		</bndbox>
	</object>
	<object>
		<name>n</name>
		<pose>Unspecified</pose>
		<truncated>1</truncated>
		<difficult>0</difficult>
		<bndbox>
			<xmin>529</xmin>
			<ymin>171</ymin>
			<xmax>572</xmax>
			<ymax>191</ymax>
		</bndbox>
	</object>
	<object>
		<name>n</name>
		<pose>Unspecified</pose>
		<truncated>1</truncated>
		<difficult>0</difficult>
		<bndbox>
			<xmin>470</xmin>
			<ymin>135</ymin>
			<xmax>495</xmax>
			<ymax>149</ymax>
		</bndbox>
	</object>
</annotation>