<annotation>
	<folder>WH_data</folder>
	<filename>12592.JPEG</filename>
	<source>
		<database>WH Data</database>
		<annotation>WH</annotation>
		<image>flickr</image>
		<flickrid>NULL</flickrid>
	</source>
	<owner>
		<flickrid>NULL</flickrid>
		<name>WH</name>
	</owner>
	<size>
		<width>820</width>
		<height>581</height>
		<depth>3</depth>
	</size>
		<segmented>0</segmented>
	<object>
		<name>n</name>
		<pose>Unspecified</pose>
		<truncated>1</truncated>
		<difficult>0</difficult>
		<bndbox>
			<xmin>344</xmin>
			<ymin>217</ymin>
			<xmax>389</xmax>
			<ymax>240</ymax>
		</bndbox>
	</object>
</annotation>